launch.py
ios_backup/__init__.py
ios_backup/__main__.py
ios_backup/backup.py
ios_backup/db.py
ios_backup_browser-0.1.0.dist-info/licenses/LICENSE
ios_backup_browser-0.1.0.dist-info/METADATA
ios_backup_browser-0.1.0.dist-info/WHEEL
ios_backup_browser-0.1.0.dist-info/top_level.txt
ios_backup_browser-0.1.0.dist-info/RECORD
