Metadata-Version: 2.4
Name: ios-backup-browser
Version: 0.1.0
Summary: Browser and exporter for iOS backups
Requires-Python: >=3.10
License-File: LICENSE
Dynamic: license-file
